pcm/__init__.py
pcm/cli.py
pcm/func.py
pcm/render.py
pcm/requirements.py
pcm/util.py
pcm/templates/A.json.template
pcm/templates/Grid.txt.template
pcm/templates/NGXGPActuator.cfg.template
pcm/templates/NoIrradiation.json.template
pcm/templates/alt_config.xml.template
pcm/templates/arar_constants.ini.template
pcm/templates/argus_mftable.csv.template
pcm/templates/canvas.xml.template
pcm/templates/canvas.yaml.template
pcm/templates/canvas_config.xml.template
pcm/templates/credentials.json.template
pcm/templates/defaults.yaml.template
pcm/templates/dvc.ini.template
pcm/templates/example_extraction.py.template
pcm/templates/example_post_equilibration.py.template
pcm/templates/example_post_measurement.py.template
pcm/templates/example_procedure.py.template
pcm/templates/example_unknown.py.template
pcm/templates/experiment_defaults.yaml.template
pcm/templates/extractionline.ini.template
pcm/templates/general.ini.template
pcm/templates/hops.yaml.template
pcm/templates/initialization.xml.template
pcm/templates/launcher_mac.template
pcm/templates/launcher_mac_conda.template
pcm/templates/launcher_pc.template
pcm/templates/ngx.ini.template
pcm/templates/ngx_config.cfg.template
pcm/templates/ngx_detectors.yaml.template
pcm/templates/ngx_mftable.csv.template
pcm/templates/ngx_switch_controller.cfg.template
pcm/templates/nominal.yaml.template
pcm/templates/productions.json.template
pcm/templates/spectrometer_microcontroller.cfg.template
pcm/templates/startup_tests.yaml.template
pcm/templates/system_monitor.cfg.template
pcm/templates/update.ini.template
pcm/templates/valves.yaml.template
pychron_cm-0.3.30.dist-info/LICENSE
pychron_cm-0.3.30.dist-info/METADATA
pychron_cm-0.3.30.dist-info/WHEEL
pychron_cm-0.3.30.dist-info/entry_points.txt
pychron_cm-0.3.30.dist-info/top_level.txt
pychron_cm-0.3.30.dist-info/RECORD
