Metadata-Version: 2.1
Name: pychron-cm
Version: 0.3.30
Summary: Pychron configuration manager
Home-page: https://github.com/PychronLabsLLC/pcm
Author: Jake Ross
Classifier: Programming Language :: Python :: 3
Classifier: Operating System :: OS Independent
Requires-Python: >=3.6
License-File: LICENSE
Requires-Dist: Click
Requires-Dist: pyyaml
Requires-Dist: gitpython
Requires-Dist: requests
